{
  "texto_completo": "$.7=V PagomovilBDVPersonas 104,52Bs , Fecha : 20/06/ 2025 Operacin : 003039243692 I_|:| Identificacin : 27061025 Origen : 0102 **** 2716 Destino : 04125318244 Banco : 0105 - BANCOMERCANTIL",
  "total_caracteres": 188,
  "tiempo_procesamiento": 0.954,
  "metodo_extraccion": "ELITE_SINGLE_PASS",
  "configuracion_tesseract": "high_confidence",
  "imagen_elite_valores_unicos": 2,
  "estadisticas_ocr": {
    "total_palabras": 30,
    "palabras_validas": 17,
    "confianza_promedio": 54.65,
    "confianza_minima": 0,
    "confianza_maxima": 96,
    "palabras_alta_confianza": 9,
    "palabras_baja_confianza": 7,
    "distribucion_confianza": {
      "excelente (90-100)": 7,
      "buena (70-89)": 2,
      "regular (50-69)": 1,
      "baja (30-49)": 0,
      "muy_baja (0-29)": 7
    }
  },
  "palabras_detectadas": [
    {
      "texto": "003039243692",
      "confianza": 96,
      "posicion": {
        "x": 437,
        "y": 461,
        "width": 190,
        "height": 19
      },
      "categoria_confianza": "excelente"
    },
    {
      "texto": "04125318244",
      "confianza": 96,
      "posicion": {
        "x": 488,
        "y": 635,
        "width": 175,
        "height": 19
      },
      "categoria_confianza": "excelente"
    },
    {
      "texto": "27061025",
      "confianza": 94,
      "posicion": {
        "x": 536,
        "y": 513,
        "width": 126,
        "height": 31
      },
      "categoria_confianza": "excelente"
    },
    {
      "texto": "Fecha:",
      "confianza": 93,
      "posicion": {
        "x": 58,
        "y": 395,
        "width": 73,
        "height": 38
      },
      "categoria_confianza": "excelente"
    },
    {
      "texto": "Destino:",
      "confianza": 93,
      "posicion": {
        "x": 58,
        "y": 625,
        "width": 96,
        "height": 39
      },
      "categoria_confianza": "excelente"
    },
    {
      "texto": "20/06/2025",
      "confianza": 92,
      "posicion": {
        "x": 521,
        "y": 398,
        "width": 142,
        "height": 27
      },
      "categoria_confianza": "excelente"
    },
    {
      "texto": "Origen:",
      "confianza": 92,
      "posicion": {
        "x": 57,
        "y": 573,
        "width": 86,
        "height": 33
      },
      "categoria_confianza": "excelente"
    },
    {
      "texto": "Banco:",
      "confianza": 89,
      "posicion": {
        "x": 58,
        "y": 683,
        "width": 78,
        "height": 39
      },
      "categoria_confianza": "buena"
    },
    {
      "texto": ",",
      "confianza": 73,
      "posicion": {
        "x": 671,
        "y": 345,
        "width": 1,
        "height": 5
      },
      "categoria_confianza": "buena"
    },
    {
      "texto": "I_|:|",
      "confianza": 60,
      "posicion": {
        "x": 642,
        "y": 450,
        "width": 28,
        "height": 33
      },
      "categoria_confianza": "aceptable"
    },
    {
      "texto": "$.7=V",
      "confianza": 26,
      "posicion": {
        "x": 315,
        "y": 50,
        "width": 86,
        "height": 70
      },
      "categoria_confianza": "baja"
    },
    {
      "texto": "0102****2716",
      "confianza": 25,
      "posicion": {
        "x": 488,
        "y": 577,
        "width": 175,
        "height": 25
      },
      "categoria_confianza": "baja"
    },
    {
      "texto": "PagomovilBDVPersonas",
      "confianza": 0,
      "posicion": {
        "x": 161,
        "y": 164,
        "width": 399,
        "height": 36
      },
      "categoria_confianza": "baja"
    },
    {
      "texto": "104,52Bs",
      "confianza": 0,
      "posicion": {
        "x": 280,
        "y": 310,
        "width": 162,
        "height": 32
      },
      "categoria_confianza": "baja"
    },
    {
      "texto": "Operacin:",
      "confianza": 0,
      "posicion": {
        "x": 57,
        "y": 455,
        "width": 127,
        "height": 34
      },
      "categoria_confianza": "baja"
    },
    {
      "texto": "Identificacin:",
      "confianza": 0,
      "posicion": {
        "x": 58,
        "y": 509,
        "width": 162,
        "height": 39
      },
      "categoria_confianza": "baja"
    },
    {
      "texto": "0105-BANCOMERCANTIL",
      "confianza": 0,
      "posicion": {
        "x": 321,
        "y": 686,
        "width": 343,
        "height": 27
      },
      "categoria_confianza": "baja"
    }
  ],
  "confianza_promedio": {
    "simple": 54.65,
    "ponderada": 44.49,
    "palabras_evaluadas": 17
  },
  "calidad_extraccion": {
    "caracteres_totales": 161,
    "palabras_totales": 28,
    "densidad_informacion": 0.856,
    "errores_detectados": [
      "Caracteres sospechosos: 4"
    ],
    "puntuacion_calidad": 64.64705882352942,
    "categoria": "Buena",
    "recomendaciones": [
      "Revisar manualmente caracteres especiales detectados"
    ]
  },
  "deteccion_inteligente": {
    "tipo_imagen": "documento_escaneado",
    "esquema_color": "texto_oscuro_fondo_claro",
    "inversion_requerida": false,
    "ui_elements_detectados": true,
    "aspect_ratio": 0.9266409266409267,
    "calidad_digital": false,
    "dark_percentage": 3.6297011375427246,
    "light_percentage": 96.37030029296875,
    "edge_density": 0.025577363077363077,
    "noise_estimate": 60.6119043546338,
    "confianza_deteccion": 0.4
  },
  "datos_financieros": {
    "amount": [
      {
        "valor": "7",
        "posicion_texto": 2
      },
      {
        "valor": "104,52",
        "posicion_texto": 27
      },
      {
        "valor": "20",
        "posicion_texto": 46
      },
      {
        "valor": "06",
        "posicion_texto": 49
      },
      {
        "valor": "202",
        "posicion_texto": 53
      }
    ],
    "phone": [
      {
        "valor": "00303924369",
        "posicion_texto": 69
      },
      {
        "valor": "04125318244",
        "posicion_texto": 147
      }
    ],
    "analisis_documento": {
      "tipo": "desconocido",
      "confianza": 0,
      "keywords_encontradas": []
    },
    "resumen_extraido": {
      "montos_encontrados": 5,
      "fechas_encontradas": 0,
      "referencias_encontradas": 0,
      "cuentas_encontradas": 0,
      "telefonos_encontrados": 2,
      "total_elementos": 7,
      "completitud_porcentaje": 50
    }
  },
  "tiempo": 0.959
}