{
  "request_id": "2025-07-06-_3sadad@s31_matias_11:01.png",
  "processing_status": "success",
  "error_reason": null,
  "metadata": {
    "fecha_procesamiento": "2025-07-06T05:38:01.862433",
    "perfil_ocr_usado": "unknown",
    "tiempo_procesamiento_ms": 463.74,
    "fuente_whatsapp": {
      "sender_id": "3sadad@s31",
      "sender_name_registered": "matias",
      "fecha_envio_whatsapp": "2025-07-06",
      "hora_envio_whatsapp": "11:01",
      "sorteo_fecha": "2025-07-06",
      "sorteo_conteo": "",
      "caption_whatsapp": "21 33"
    }
  },
  "full_raw_ocr_text": "20/06/2025 - 06:50:24 pm Mercantil Envio de Tpago Operacion realizada Desde mi cuenta Se Envio (Bs.) AI beneficiario Cuental de Ahorro 3976 210,00 0412 244 Banco Mercantil, C.A. S.A.C.A, Banco Universal Bingo trebol V-27.061.025 Concepto Nro. Referencia Fecha y hora 106 93 48311146148 20/06/2025 - 06:50:20 Lai informacion: mestrada: en: OSIEI pagina: es confidencial",
  "extracted_fields": [
    {
      "field_name": "numero_referencia",
      "value": "20/06/2025",
      "confidence": 0.958,
      "coordinates": [
        0,
        0,
        0,
        0
      ],
      "relative_position": "middle-center",
      "raw_text_segment": "Nro. 20/06/2025"
    },
    {
      "field_name": "banco_origen",
      "value": "20/06/2025",
      "confidence": 0.969,
      "coordinates": [
        0,
        0,
        0,
        0
      ],
      "relative_position": "middle-center",
      "raw_text_segment": "Banco 20/06/2025"
    },
    {
      "field_name": "cedula_beneficiario",
      "value": "20/06/2025",
      "confidence": 0.961,
      "coordinates": [
        0,
        0,
        0,
        0
      ],
      "relative_position": "middle-center",
      "raw_text_segment": "Operacion 20/06/2025"
    },
    {
      "field_name": "nombre_beneficiario",
      "value": "20/06/2025",
      "confidence": 0.744,
      "coordinates": [
        0,
        0,
        0,
        0
      ],
      "relative_position": "middle-center",
      "raw_text_segment": "beneficiario 20/06/2025"
    },
    {
      "field_name": "fecha_transaccion",
      "value": "20/06/2025",
      "confidence": 0.969,
      "coordinates": [
        0,
        0,
        0,
        0
      ],
      "relative_position": "middle-center",
      "raw_text_segment": "hora 20/06/2025"
    },
    {
      "field_name": "tipo_transaccion",
      "value": "20/06/2025",
      "confidence": 0.971,
      "coordinates": [
        0,
        0,
        0,
        0
      ],
      "relative_position": "middle-center",
      "raw_text_segment": "Tpago 20/06/2025"
    },
    {
      "field_name": "descripcion_motivo",
      "value": "21 33",
      "confidence": 1.0,
      "coordinates": null,
      "relative_position": null,
      "raw_text_segment": null
    }
  ],
  "unmapped_text_segments": [
    {
      "text": "20/06/2025",
      "confidence": 0.9419072270393372,
      "coordinates": [
        0,
        0,
        0,
        0
      ],
      "relative_position": "middle-center"
    },
    {
      "text": "-",
      "confidence": 0.9826095104217529,
      "coordinates": [
        0,
        0,
        0,
        0
      ],
      "relative_position": "middle-center"
    },
    {
      "text": "06:50:24",
      "confidence": 0.9979094862937927,
      "coordinates": [
        0,
        0,
        0,
        0
      ],
      "relative_position": "middle-center"
    },
    {
      "text": "pm",
      "confidence": 0.9293264746665955,
      "coordinates": [
        0,
        0,
        0,
        0
      ],
      "relative_position": "middle-center"
    },
    {
      "text": "Mercantil",
      "confidence": 0.9773082137107849,
      "coordinates": [
        0,
        0,
        0,
        0
      ],
      "relative_position": "middle-center"
    },
    {
      "text": "Envio",
      "confidence": 0.5062887668609619,
      "coordinates": [
        0,
        0,
        0,
        0
      ],
      "relative_position": "middle-center"
    },
    {
      "text": "de",
      "confidence": 0.9994413256645203,
      "coordinates": [
        0,
        0,
        0,
        0
      ],
      "relative_position": "middle-center"
    },
    {
      "text": "Tpago",
      "confidence": 0.9995810389518738,
      "coordinates": [
        0,
        0,
        0,
        0
      ],
      "relative_position": "middle-center"
    },
    {
      "text": "Operacion",
      "confidence": 0.979278564453125,
      "coordinates": [
        0,
        0,
        0,
        0
      ],
      "relative_position": "middle-center"
    },
    {
      "text": "realizada",
      "confidence": 0.8965017199516296,
      "coordinates": [
        0,
        0,
        0,
        0
      ],
      "relative_position": "middle-center"
    },
    {
      "text": "Desde",
      "confidence": 0.9279981851577759,
      "coordinates": [
        0,
        0,
        0,
        0
      ],
      "relative_position": "middle-center"
    },
    {
      "text": "mi",
      "confidence": 0.955430269241333,
      "coordinates": [
        0,
        0,
        0,
        0
      ],
      "relative_position": "middle-center"
    },
    {
      "text": "cuenta",
      "confidence": 0.9853721261024475,
      "coordinates": [
        0,
        0,
        0,
        0
      ],
      "relative_position": "middle-center"
    },
    {
      "text": "Se",
      "confidence": 0.9859665036201477,
      "coordinates": [
        0,
        0,
        0,
        0
      ],
      "relative_position": "middle-center"
    },
    {
      "text": "Envio",
      "confidence": 0.9330092668533325,
      "coordinates": [
        0,
        0,
        0,
        0
      ],
      "relative_position": "middle-center"
    },
    {
      "text": "(Bs.)",
      "confidence": 0.7505127191543579,
      "coordinates": [
        0,
        0,
        0,
        0
      ],
      "relative_position": "middle-center"
    },
    {
      "text": "AI",
      "confidence": 0.6010663509368896,
      "coordinates": [
        0,
        0,
        0,
        0
      ],
      "relative_position": "middle-center"
    },
    {
      "text": "beneficiario",
      "confidence": 0.5466539859771729,
      "coordinates": [
        0,
        0,
        0,
        0
      ],
      "relative_position": "middle-center"
    },
    {
      "text": "Cuental",
      "confidence": 0.9553743600845337,
      "coordinates": [
        0,
        0,
        0,
        0
      ],
      "relative_position": "middle-center"
    },
    {
      "text": "de",
      "confidence": 0.9960731267929077,
      "coordinates": [
        0,
        0,
        0,
        0
      ],
      "relative_position": "middle-center"
    },
    {
      "text": "Ahorro",
      "confidence": 0.94912189245224,
      "coordinates": [
        0,
        0,
        0,
        0
      ],
      "relative_position": "middle-center"
    },
    {
      "text": "3976",
      "confidence": 0.696294367313385,
      "coordinates": [
        0,
        0,
        0,
        0
      ],
      "relative_position": "middle-center"
    },
    {
      "text": "210,00",
      "confidence": 0.9990779161453247,
      "coordinates": [
        0,
        0,
        0,
        0
      ],
      "relative_position": "middle-center"
    },
    {
      "text": "0412",
      "confidence": 0.9886915683746338,
      "coordinates": [
        0,
        0,
        0,
        0
      ],
      "relative_position": "middle-center"
    },
    {
      "text": "244",
      "confidence": 0.5358675718307495,
      "coordinates": [
        0,
        0,
        0,
        0
      ],
      "relative_position": "middle-center"
    },
    {
      "text": "Banco",
      "confidence": 0.9964792132377625,
      "coordinates": [
        0,
        0,
        0,
        0
      ],
      "relative_position": "middle-center"
    },
    {
      "text": "Mercantil,",
      "confidence": 0.9178282618522644,
      "coordinates": [
        0,
        0,
        0,
        0
      ],
      "relative_position": "middle-center"
    },
    {
      "text": "C.A.",
      "confidence": 0.9915252327919006,
      "coordinates": [
        0,
        0,
        0,
        0
      ],
      "relative_position": "middle-center"
    },
    {
      "text": "S.A.C.A,",
      "confidence": 0.6275579929351807,
      "coordinates": [
        0,
        0,
        0,
        0
      ],
      "relative_position": "middle-center"
    },
    {
      "text": "Banco",
      "confidence": 0.9720693826675415,
      "coordinates": [
        0,
        0,
        0,
        0
      ],
      "relative_position": "middle-center"
    },
    {
      "text": "Universal",
      "confidence": 0.9934694766998291,
      "coordinates": [
        0,
        0,
        0,
        0
      ],
      "relative_position": "middle-center"
    },
    {
      "text": "Bingo",
      "confidence": 0.9883773922920227,
      "coordinates": [
        0,
        0,
        0,
        0
      ],
      "relative_position": "middle-center"
    },
    {
      "text": "trebol",
      "confidence": 0.9961374402046204,
      "coordinates": [
        0,
        0,
        0,
        0
      ],
      "relative_position": "middle-center"
    },
    {
      "text": "V-27.061.025",
      "confidence": 0.8673589825630188,
      "coordinates": [
        0,
        0,
        0,
        0
      ],
      "relative_position": "middle-center"
    },
    {
      "text": "Concepto",
      "confidence": 0.9992357492446899,
      "coordinates": [
        0,
        0,
        0,
        0
      ],
      "relative_position": "middle-center"
    },
    {
      "text": "Nro.",
      "confidence": 0.9746063947677612,
      "coordinates": [
        0,
        0,
        0,
        0
      ],
      "relative_position": "middle-center"
    },
    {
      "text": "Referencia",
      "confidence": 0.5568471550941467,
      "coordinates": [
        0,
        0,
        0,
        0
      ],
      "relative_position": "middle-center"
    },
    {
      "text": "Fecha",
      "confidence": 0.9899565577507019,
      "coordinates": [
        0,
        0,
        0,
        0
      ],
      "relative_position": "middle-center"
    },
    {
      "text": "y",
      "confidence": 0.9991061091423035,
      "coordinates": [
        0,
        0,
        0,
        0
      ],
      "relative_position": "middle-center"
    },
    {
      "text": "hora",
      "confidence": 0.9966443777084351,
      "coordinates": [
        0,
        0,
        0,
        0
      ],
      "relative_position": "middle-center"
    },
    {
      "text": "106",
      "confidence": 0.9929091930389404,
      "coordinates": [
        0,
        0,
        0,
        0
      ],
      "relative_position": "middle-center"
    },
    {
      "text": "93",
      "confidence": 0.9959025979042053,
      "coordinates": [
        0,
        0,
        0,
        0
      ],
      "relative_position": "middle-center"
    },
    {
      "text": "48311146148",
      "confidence": 0.9897391200065613,
      "coordinates": [
        0,
        0,
        0,
        0
      ],
      "relative_position": "middle-center"
    },
    {
      "text": "20/06/2025",
      "confidence": 0.8865765929222107,
      "coordinates": [
        0,
        0,
        0,
        0
      ],
      "relative_position": "middle-center"
    },
    {
      "text": "-",
      "confidence": 0.9998645782470703,
      "coordinates": [
        0,
        0,
        0,
        0
      ],
      "relative_position": "middle-center"
    },
    {
      "text": "06:50:20",
      "confidence": 0.9698106646537781,
      "coordinates": [
        0,
        0,
        0,
        0
      ],
      "relative_position": "middle-center"
    },
    {
      "text": "Lai",
      "confidence": 0.4033341109752655,
      "coordinates": [
        0,
        0,
        0,
        0
      ],
      "relative_position": "middle-center"
    },
    {
      "text": "informacion:",
      "confidence": 0.9624173641204834,
      "coordinates": [
        0,
        0,
        0,
        0
      ],
      "relative_position": "middle-center"
    },
    {
      "text": "mestrada:",
      "confidence": 0.5169653296470642,
      "coordinates": [
        0,
        0,
        0,
        0
      ],
      "relative_position": "middle-center"
    },
    {
      "text": "en:",
      "confidence": 0.544252872467041,
      "coordinates": [
        0,
        0,
        0,
        0
      ],
      "relative_position": "middle-center"
    },
    {
      "text": "OSIEI",
      "confidence": 0.4720498323440552,
      "coordinates": [
        0,
        0,
        0,
        0
      ],
      "relative_position": "middle-center"
    },
    {
      "text": "pagina:",
      "confidence": 0.5158010125160217,
      "coordinates": [
        0,
        0,
        0,
        0
      ],
      "relative_position": "middle-center"
    },
    {
      "text": "es",
      "confidence": 0.9923825860023499,
      "coordinates": [
        0,
        0,
        0,
        0
      ],
      "relative_position": "middle-center"
    },
    {
      "text": "confidencial",
      "confidence": 0.5189787745475769,
      "coordinates": [
        0,
        0,
        0,
        0
      ],
      "relative_position": "middle-center"
    }
  ],
  "batch_metadata": {
    "batch_size": 3,
    "batch_processing_time_seconds": 1.98,
    "batch_timestamp": "2025-07-06T05:38:02.275355"
  },
  "batch_id": "BATCH_20250706_053800_292",
  "batch_processing_time": 1.98,
  "batch_position": 2,
  "batch_size": 3
}