{
  "imagen_info": {
    "ancho": 816,
    "alto": 1056,
    "resolucion_total": 861696,
    "canales": 3,
    "modo": "RGB",
    "formato": "JPEG",
    "brillo_promedio": 251.86037419229055,
    "desviacion_brillo": 20.33515088147026,
    "rango_dinamico": 255.0,
    "histogram": [
      249.0,
      11.0,
      13.0,
      21.0,
      26.0,
      8.0,
      11.0,
      12.0,
      14.0,
      15.0,
      25.0,
      12.0,
      16.0,
      11.0,
      11.0,
      23.0,
      20.0,
      18.0,
      21.0,
      20.0,
      20.0,
      29.0,
      20.0,
      21.0,
      26.0,
      26.0,
      32.0,
      25.0,
      41.0,
      50.0,
      52.0,
      50.0,
      59.0,
      33.0,
      56.0,
      43.0,
      61.0,
      53.0,
      86.0,
      79.0,
      76.0,
      77.0,
      88.0,
      81.0,
      101.0,
      94.0,
      91.0,
      131.0,
      98.0,
      123.0,
      114.0,
      102.0,
      104.0,
      115.0,
      114.0,
      101.0,
      109.0,
      112.0,
      135.0,
      117.0,
      116.0,
      105.0,
      100.0,
      109.0,
      109.0,
      115.0,
      118.0,
      100.0,
      98.0,
      97.0,
      110.0,
      84.0,
      99.0,
      84.0,
      96.0,
      105.0,
      93.0,
      103.0,
      95.0,
      79.0,
      76.0,
      98.0,
      85.0,
      83.0,
      83.0,
      69.0,
      81.0,
      90.0,
      93.0,
      77.0,
      65.0,
      76.0,
      81.0,
      77.0,
      75.0,
      81.0,
      86.0,
      72.0,
      63.0,
      82.0,
      76.0,
      83.0,
      61.0,
      55.0,
      75.0,
      78.0,
      75.0,
      57.0,
      64.0,
      63.0,
      70.0,
      75.0,
      52.0,
      55.0,
      60.0,
      68.0,
      62.0,
      72.0,
      50.0,
      76.0,
      62.0,
      77.0,
      65.0,
      60.0,
      75.0,
      66.0,
      71.0,
      61.0,
      55.0,
      54.0,
      53.0,
      56.0,
      72.0,
      68.0,
      54.0,
      68.0,
      57.0,
      49.0,
      43.0,
      70.0,
      62.0,
      52.0,
      54.0,
      46.0,
      57.0,
      49.0,
      66.0,
      38.0,
      48.0,
      60.0,
      52.0,
      43.0,
      54.0,
      67.0,
      53.0,
      47.0,
      52.0,
      58.0,
      43.0,
      73.0,
      61.0,
      54.0,
      62.0,
      55.0,
      58.0,
      56.0,
      74.0,
      50.0,
      55.0,
      54.0,
      64.0,
      71.0,
      62.0,
      64.0,
      44.0,
      64.0,
      53.0,
      67.0,
      51.0,
      45.0,
      47.0,
      57.0,
      52.0,
      48.0,
      58.0,
      48.0,
      51.0,
      53.0,
      55.0,
      60.0,
      50.0,
      55.0,
      35.0,
      60.0,
      63.0,
      69.0,
      49.0,
      51.0,
      60.0,
      54.0,
      55.0,
      52.0,
      76.0,
      59.0,
      56.0,
      64.0,
      70.0,
      57.0,
      77.0,
      65.0,
      70.0,
      71.0,
      72.0,
      73.0,
      68.0,
      90.0,
      58.0,
      83.0,
      84.0,
      78.0,
      91.0,
      78.0,
      104.0,
      97.0,
      115.0,
      123.0,
      116.0,
      119.0,
      118.0,
      144.0,
      136.0,
      149.0,
      163.0,
      175.0,
      959.0,
      1045.0,
      1082.0,
      1102.0,
      21796.0,
      1931.0,
      261.0,
      234.0,
      239.0,
      1042.0,
      1113.0,
      323.0,
      350.0,
      421.0,
      601.0,
      610.0,
      814.0,
      1359.0,
      1587.0,
      3411.0,
      10440.0,
      794884.0
    ],
    "histogram_analysis": {
      "picos_principales": [
        [
          238,
          21796
        ]
      ],
      "rango_fondo_sugerido": 255,
      "rango_texto_sugerido": 0,
      "distribucion": {
        "oscuras": 0.006895703263580799,
        "medias": 0.006322415545582771,
        "claras": 0.986781895160675
      },
      "requiere_inversion": false,
      "bimodal": false
    },
    "variaciones_fondo": {
      "total_regiones_analizadas": 1271,
      "fondos_unicos_detectados": 3,
      "variacion_fondos": 2.622477153886162,
      "fondos_heterogeneos": false,
      "rango_fondos": [
        238,
        255
      ],
      "requiere_unificacion_avanzada": false,
      "regiones_variacion": [
        {
          "posicion": [
            0,
            0
          ],
          "media_local": 254.9996,
          "std_local": 0.01999599959991998,
          "pico_fondo": 255
        },
        {
          "posicion": [
            25,
            0
          ],
          "media_local": 254.986,
          "std_local": 0.11749042514179613,
          "pico_fondo": 255
        },
        {
          "posicion": [
            50,
            0
          ],
          "media_local": 254.9636,
          "std_local": 0.20168053946774342,
          "pico_fondo": 255
        },
        {
          "posicion": [
            75,
            0
          ],
          "media_local": 254.9772,
          "std_local": 0.16697353083647723,
          "pico_fondo": 255
        },
        {
          "posicion": [
            100,
            0
          ],
          "media_local": 255.0,
          "std_local": 0.0,
          "pico_fondo": 255
        },
        {
          "posicion": [
            125,
            0
          ],
          "media_local": 255.0,
          "std_local": 0.0,
          "pico_fondo": 255
        },
        {
          "posicion": [
            150,
            0
          ],
          "media_local": 254.9856,
          "std_local": 0.12566877098149723,
          "pico_fondo": 255
        },
        {
          "posicion": [
            175,
            0
          ],
          "media_local": 254.8464,
          "std_local": 3.438430897953309,
          "pico_fondo": 255
        },
        {
          "posicion": [
            200,
            0
          ],
          "media_local": 253.0924,
          "std_local": 18.682651370723587,
          "pico_fondo": 255
        },
        {
          "posicion": [
            225,
            0
          ],
          "media_local": 253.2148,
          "std_local": 18.37615468371988,
          "pico_fondo": 255
        }
      ]
    }
  },
  "calidad_imagen": {
    "contraste": 20.33515088147026,
    "blur_variance": 1160.6415209076054,
    "entropy": 0.772429347038269,
    "gradiente_promedio": 16.1143441445348,
    "brillo_promedio": 251.86037419229055,
    "uniformidad_brillo": 20.33515088147026,
    "calificacion_calidad": 50
  },
  "deteccion_texto": {
    "regiones_detectadas": 31,
    "area_total_texto": 45215,
    "densidad_texto": 0.05247210153000594,
    "regiones": [
      {
        "x": 636,
        "y": 385,
        "width": 64,
        "height": 17,
        "area": 1088,
        "aspect_ratio": 3.764705882352941
      },
      {
        "x": 539,
        "y": 385,
        "width": 96,
        "height": 18,
        "area": 1728,
        "aspect_ratio": 5.333333333333333
      },
      {
        "x": 281,
        "y": 385,
        "width": 101,
        "height": 17,
        "area": 1717,
        "aspect_ratio": 5.9411764705882355
      },
      {
        "x": 23,
        "y": 385,
        "width": 51,
        "height": 17,
        "area": 867,
        "aspect_ratio": 3.0
      },
      {
        "x": 540,
        "y": 362,
        "width": 94,
        "height": 19,
        "area": 1786,
        "aspect_ratio": 4.947368421052632
      },
      {
        "x": 281,
        "y": 362,
        "width": 33,
        "height": 16,
        "area": 528,
        "aspect_ratio": 2.0625
      },
      {
        "x": 22,
        "y": 362,
        "width": 72,
        "height": 18,
        "area": 1296,
        "aspect_ratio": 4.0
      },
      {
        "x": 316,
        "y": 361,
        "width": 79,
        "height": 17,
        "area": 1343,
        "aspect_ratio": 4.647058823529412
      },
      {
        "x": 539,
        "y": 315,
        "width": 93,
        "height": 16,
        "area": 1488,
        "aspect_ratio": 5.8125
      },
      {
        "x": 539,
        "y": 293,
        "width": 78,
        "height": 20,
        "area": 1560,
        "aspect_ratio": 3.9
      },
      {
        "x": 539,
        "y": 273,
        "width": 61,
        "height": 16,
        "area": 976,
        "aspect_ratio": 3.8125
      },
      {
        "x": 539,
        "y": 229,
        "width": 99,
        "height": 17,
        "area": 1683,
        "aspect_ratio": 5.823529411764706
      },
      {
        "x": 281,
        "y": 229,
        "width": 51,
        "height": 19,
        "area": 969,
        "aspect_ratio": 2.6842105263157894
      },
      {
        "x": 93,
        "y": 207,
        "width": 52,
        "height": 15,
        "area": 780,
        "aspect_ratio": 3.466666666666667
      },
      {
        "x": 539,
        "y": 206,
        "width": 18,
        "height": 15,
        "area": 270,
        "aspect_ratio": 1.2
      },
      {
        "x": 281,
        "y": 206,
        "width": 21,
        "height": 16,
        "area": 336,
        "aspect_ratio": 1.3125
      },
      {
        "x": 71,
        "y": 206,
        "width": 21,
        "height": 15,
        "area": 315,
        "aspect_ratio": 1.4
      },
      {
        "x": 558,
        "y": 205,
        "width": 88,
        "height": 17,
        "area": 1496,
        "aspect_ratio": 5.176470588235294
      },
      {
        "x": 303,
        "y": 205,
        "width": 42,
        "height": 17,
        "area": 714,
        "aspect_ratio": 2.4705882352941178
      },
      {
        "x": 22,
        "y": 205,
        "width": 48,
        "height": 17,
        "area": 816,
        "aspect_ratio": 2.823529411764706
      }
    ],
    "cobertura_texto_porcentaje": 5.247210153000594
  },
  "ruido_artefactos": {
    "nivel_ruido": 1.609408654560309,
    "desviacion_ruido": 9.60246465774745,
    "porcentaje_pixeles_ruidosos": 2.628653260546643,
    "uniformidad": 1.7543228702465834,
    "calificacion_ruido": "Bajo"
  },
  "geometria_orientacion": {
    "sesgo_estimado": 2.5,
    "lineas_detectadas": 50,
    "simetria_horizontal": 0.1365356147289276,
    "relacion_aspecto": 0.7727272727272727,
    "requiere_deskew": true,
    "orientacion_correcta": true
  },
  "deteccion_inteligente": {
    "tipo_imagen": "documento_escaneado",
    "esquema_color": "texto_oscuro_fondo_claro",
    "inversion_requerida": false,
    "ui_elements_detectados": false,
    "aspect_ratio": 0.7727272727272727,
    "calidad_digital": false,
    "dark_percentage": 1.041434645652771,
    "light_percentage": 98.95856475830078,
    "edge_density": 0.014473781937017231,
    "noise_estimate": 43.930168578506034,
    "confianza_deteccion": 0.2
  },
  "recomendaciones": {
    "perfil_recomendado": "rapido",
    "aplicar_deskew": true,
    "nivel_denoise": "moderado",
    "ajuste_contraste": true,
    "filtro_bilateral": true,
    "prioridades": [
      "Corrección de sesgo necesaria",
      "Mejorar contraste"
    ]
  },
  "puntuacion_general": {
    "total": 57.9,
    "calidad": 50,
    "texto": 26.2,
    "ruido": 100,
    "geometria": 100,
    "categoria": "Regular"
  }
}